{
	"name": "openDataExport",
	"properties": {
		"activities": [
			{
				"name": "CacheRegions",
				"type": "Copy",
				"dependsOn": [],
				"policy": {
					"timeout": "7.00:00:00",
					"retry": 0,
					"retryIntervalInSeconds": 30,
					"secureOutput": false,
					"secureInput": false
				},
				"userProperties": [],
				"typeProperties": {
					"source": {
						"type": "JsonSource",
						"storeSettings": {
							"type": "HttpReadSettings",
							"requestMethod": "GET"
						},
						"formatSettings": {
							"type": "JsonReadSettings"
						}
					},
					"sink": {
						"type": "JsonSink",
						"storeSettings": {
							"type": "AzureBlobStorageWriteSettings"
						},
						"formatSettings": {
							"type": "JsonWriteSettings",
							"quoteAllText": true
						}
					},
					"enableStaging": false
				},
				"inputs": [
					{
						"referenceName": "github_Regions",
						"type": "DatasetReference"
					}
				],
				"outputs": [
					{
						"referenceName": "openData_Cache_Regions",
						"type": "DatasetReference"
					}
				]
			},
			{
				"name": "ExportProviders",
				"type": "ExecuteDataFlow",
				"dependsOn": [
					{
						"activity": "CacheCourses",
						"dependencyConditions": [
							"Succeeded"
						]
					}
				],
				"policy": {
					"timeout": "7.00:00:00",
					"retry": 0,
					"retryIntervalInSeconds": 30,
					"secureOutput": false,
					"secureInput": false
				},
				"userProperties": [],
				"typeProperties": {
					"dataflow": {
						"referenceName": "openData_Transform_Providers",
						"type": "DataFlowReference"
					},
					"compute": {
						"coreCount": 8,
						"computeType": "General"
					}
				}
			},
			{
				"name": "CacheCourses",
				"type": "ExecuteDataFlow",
				"dependsOn": [],
				"policy": {
					"timeout": "7.00:00:00",
					"retry": 0,
					"retryIntervalInSeconds": 30,
					"secureOutput": false,
					"secureInput": false
				},
				"userProperties": [],
				"typeProperties": {
					"dataflow": {
						"referenceName": "openData_Course_GetCurrentCourses",
						"type": "DataFlowReference"
					},
					"compute": {
						"coreCount": 8,
						"computeType": "General"
					}
				}
			},
			{
				"name": "CacheVenues",
				"type": "ExecuteDataFlow",
				"dependsOn": [
					{
						"activity": "CacheCourses",
						"dependencyConditions": [
							"Succeeded"
						]
					}
				],
				"policy": {
					"timeout": "7.00:00:00",
					"retry": 0,
					"retryIntervalInSeconds": 30,
					"secureOutput": false,
					"secureInput": false
				},
				"userProperties": [],
				"typeProperties": {
					"dataflow": {
						"referenceName": "openData_Venues_GetCourseVenues",
						"type": "DataFlowReference"
					},
					"compute": {
						"coreCount": 8,
						"computeType": "General"
					}
				}
			},
			{
				"name": "AttachCourseAddress",
				"type": "ExecuteDataFlow",
				"dependsOn": [
					{
						"activity": "CacheVenues",
						"dependencyConditions": [
							"Succeeded"
						]
					},
					{
						"activity": "CacheRegions",
						"dependencyConditions": [
							"Succeeded"
						]
					}
				],
				"policy": {
					"timeout": "7.00:00:00",
					"retry": 0,
					"retryIntervalInSeconds": 30,
					"secureOutput": false,
					"secureInput": false
				},
				"userProperties": [],
				"typeProperties": {
					"dataflow": {
						"referenceName": "openData_Course_AttachVenues",
						"type": "DataFlowReference"
					},
					"compute": {
						"coreCount": 8,
						"computeType": "General"
					}
				}
			}
		],
		"annotations": []
	}
}